Metadata-Version: 2.1
Name: pytest-pydocstyle
Version: 2.4.0
Summary: pytest plugin to run pydocstyle
Home-page: https://github.com/henry0312/pytest-pydocstyle
Author: OMOTO Tsukasa
Author-email: tsukasa@oomo.to
License: MIT
Classifier: Development Status :: 3 - Alpha
Classifier: Intended Audience :: Developers
Classifier: Topic :: Software Development :: Testing
Classifier: License :: OSI Approved :: MIT License
Classifier: Framework :: Pytest
Classifier: Programming Language :: Python :: 3
Classifier: Programming Language :: Python :: 3.9
Classifier: Programming Language :: Python :: 3.10
Classifier: Programming Language :: Python :: 3.11
Classifier: Programming Language :: Python :: 3.12
Classifier: Programming Language :: Python :: 3.13
Requires-Python: ~=3.9
License-File: LICENSE
Requires-Dist: pytest>=7.0
Requires-Dist: pydocstyle
Provides-Extra: tests
Requires-Dist: pytest-pycodestyle~=2.3; extra == "tests"
Requires-Dist: pytest-isort; extra == "tests"
